mesh_solar_power_production/__init__.py
mesh_solar_power_production/defaults.py
mesh_solar_power_production/main.py
mesh_solar_power_production/lib/__init__.py
mesh_solar_power_production/lib/solar_production_pb2.py
mesh_solar_power_production-0.0.2.dist-info/LICENSE
mesh_solar_power_production-0.0.2.dist-info/METADATA
mesh_solar_power_production-0.0.2.dist-info/WHEEL
mesh_solar_power_production-0.0.2.dist-info/top_level.txt
mesh_solar_power_production-0.0.2.dist-info/RECORD
